Workbook

Sheet APP
B2: 💰 SIMULADOR DE INVESTIMENTOS EM FIIs
B4: 👤 SEU PERFIL
B6: Salário Mensal (R$) | C6: 5000
B7: Rendimento Médio Mensal (%) | C7: 0.006
B8: Perfil de Investidor | C8: Agressivo
B9: Sugestão de Aporte (30% do salário) | C9: =C6*30% -> 1500
B11: 📊 SIMULAÇÃO DE INVESTIMENTO
B13: Quanto investir por mês? (R$) | C13: 1500
B14: Por quantos anos? | C14: 10
B15: Taxa de Rendimento Mensal (%) | C15: =C7 -> 0.006
B17: Patrimônio Acumulado | C17: =FV(C15,C14*12,-C13,0) -> 262504.51
B18: Total Investido | C18: =C13*C14*12 -> 180000
B19: Rendimento Total | C19: =C17-C18 -> 82504.514
B20: Renda Mensal Estimada | C20: =C17*C15 -> 1575.0271
B22: 🏢 ALOCAÇÃO SUGERIDA POR TIPO DE FII
B24: TIPO DE FII | C24: ALOCAÇÃO % | D24: VALOR (R$)
B25: Papel (CRI/CRA) | C25: =IFERROR(VLOOKUP(C8&"-papel",Perfis!B:E,4,FALSE()),0) -> 0.2 | D25: =C13*C25 -> 300
B26: Tijolo (Lajes/Shopping) | C26: =IFERROR(VLOOKUP(C8&"-tijolo",Perfis!B:E,4,FALSE()),0) -> 0.1 | D26: =C13*C26 -> 150
B27: Híbridos | C27: =IFERROR(VLOOKUP(C8&"-hibridos",Perfis!B:E,4,FALSE()),0) -> 0.05 | D27: =C13*C27 -> 75
B28: FOFs | C28: =IFERROR(VLOOKUP(C8&"-fofs",Perfis!B:E,4,FALSE()),0) -> 0.05 | D28: =C13*C28 -> 75
B29: Desenvolvimento | C29: =IFERROR(VLOOKUP(C8&"-desenvolvimento",Perfis!B:E,4,FALSE()),0) -> 0.4 | D29: =C13*C29 -> 600
B30: Hotelaria | C30: =IFERROR(VLOOKUP(C8&"-hotelaria",Perfis!B:E,4,FALSE()),0) -> 0.2 | D30: =C13*C30 -> 300
B31: TOTAL | C31: =SUM(C25:C30) -> 1 | D31: =SUM(D25:D30) -> 1500

Sheet Perfis
B1: CHAVE | C1: PERFIL | D1: TIPO | E1: ALOCAÇÃO %
B2: Conservador-papel | C2: Conservador | D2: papel | E2: 0.3
B3: Conservador-tijolo | C3: Conservador | D3: tijolo | E3: 0.5
B4: Conservador-hibridos | C4: Conservador | D4: hibridos | E4: 0.1
B5: Conservador-fofs | C5: Conservador | D5: fofs | E5: 0.1
B6: Conservador-desenvolvimento | C6: Conservador | D6: desenvolvimento | E6: 0
B7: Conservador-hotelaria | C7: Conservador | D7: hotelaria | E7: 0
B8: Moderado-papel | C8: Moderado | D8: papel | E8: 0.32
B9: Moderado-tijolo | C9: Moderado | D9: tijolo | E9: 0.35
B10: Moderado-hibridos | C10: Moderado | D10: hibridos | E10: 0.08
B11: Moderado-fofs | C11: Moderado | D11: fofs | E11: 0.05
B12: Moderado-desenvolvimento | C12: Moderado | D12: desenvolvimento | E12: 0.1
B13: Moderado-hotelaria | C13: Moderado | D13: hotelaria | E13: 0.1
... B19: Agressivo-hotelaria | C19: Agressivo | D19: hotelaria | E19: 0.2

Sheet Evolução
B2: 📈 EVOLUÇÃO DO PATRIMÔNIO AO LONGO DO TEMPO
B4: Ano | C4: Total Investido | D4: Patrimônio | E4: Renda Mensal
B5: 1 | C5: =APP!C13*1*12 -> 18000 | D5: =FV(APP!C15,1*12,-APP!C13,0) -> 18606.042 | E5: =D5*APP!C15 -> 111.63625
B6: 2 | C6: =APP!C13*2*12 -> 36000 | D6: =FV(APP!C15,2*12,-APP!C13,0) -> 38596.823 | E6: =D6*APP!C15 -> 231.58094
B7: 3 | C7: =APP!C13*3*12 -> 54000 | D7: =FV(APP!C15,3*12,-APP!C13,0) -> 60075.401 | E7: =D7*APP!C15 -> 360.45241
B8: 4 | C8: =APP!C13*4*12 -> 72000 | D8: =FV(APP!C15,4*12,-APP!C13,0) -> 83152.505 | E8: =D8*APP!C15 -> 498.91503
B9: 5 | C9: =APP!C13*5*12 -> 90000 | D9: =FV(APP!C15,5*12,-APP!C13,0) -> 107947.1 | E9: =D9*APP!C15 -> 647.68262
B10: 6 | C10: =APP!C13*6*12 -> 108000 | D10: =FV(APP!C15,6*12,-APP!C13,0) -> 134587.02 | E10: =D10*APP!C15 -> 807.52211
B11: 7 | C11: =APP!C13*7*12 -> 126000 | D11: =FV(APP!C15,7*12,-APP!C13,0) -> 163209.59 | E11: =D11*APP!C15 -> 979.25752
B12: 8 | C12: =APP!C13*8*12 -> 144000 | D12: =FV(APP!C15,8*12,-APP!C13,0) -> 193962.37 | E12: =D12*APP!C15 -> 1163.7742
B13: 9 | C13: =APP!C13*9*12 -> 162000 | D13: =FV(APP!C15,9*12,-APP!C13,0) -> 227003.9 | E13: =D13*APP!C15 -> 1362.0234
B14: 10 | C14: =APP!C13*10*12 -> 180000 | D14: =FV(APP!C15,10*12,-APP!C13,0) -> 262504.51 | E14: =D14*APP!C15 -> 1575.0271
B15: 11 | C15: =APP!C13*11*12 -> 198000 | D15: =FV(APP!C15,11*12,-APP!C13,0) -> 300647.24 | E15: =D15*APP!C15 -> 1803.8834
B16: 12 | C16: =APP!C13*12*12 -> 216000 | D16: =FV(APP!C15,12*12,-APP!C13,0) -> 341628.7 | E16: =D16*APP!C15 -> 2049.7722
B17: 13 | C17: =APP!C13*13*12 -> 234000 | D17: =FV(APP!C15,13*12,-APP!C13,0) -> 385660.17 | E17: =D17*APP!C15 -> 2313.961
B18: 14 | C18: =APP!C13*14*12 -> 252000 | D18: =FV(APP!C15,14*12,-APP!C13,0) -> 432968.65 | E18: =D18*APP!C15 -> 2597.8119
B19: 15 | C19: =APP!C13*15*12 -> 270000 | D19: =FV(APP!C15,15*12,-APP!C13,0) -> 483798.02 | E19: =D19*APP!C15 -> 2902.7881
B20: 16 | C20: =APP!C13*16*12 -> 288000 | D20: =FV(APP!C15,16*12,-APP!C13,0) -> 538410.33 | E20: =D20*APP!C15 -> 3230.462
B21: 17 | C21: =APP!C13*17*12 -> 306000 | D21: =FV(APP!C15,17*12,-APP!C13,0) -> 597087.11 | E21: =D21*APP!C15 -> 3582.5227
B22: 18 | C22: =APP!C13*18*12 -> 324000 | D22: =FV(APP!C15,18*12,-APP!C13,0) -> 660130.87 | E22: =D22*APP!C15 -> 3960.7852
B23: 19 | C23: =APP!C13*19*12 -> 342000 | D23: =FV(APP!C15,19*12,-APP!C13,0) -> 727866.6 | E23: =D23*APP!C15 -> 4367.1996
B24: 20 | C24: =APP!C13*20*12 -> 360000 | D24: =FV(APP!C15,20*12,-APP!C13,0) -> 800643.51 | E24: =D24*APP!C15 -> 4803.861
B25: 21 | C25: =APP!C13*21*12 -> 378000 | D25: =FV(APP!C15,21*12,-APP!C13,0) -> 878836.78 | E25: =D25*APP!C15 -> 5273.0207
B26: 22 | C26: =APP!C13*22*12 -> 396000 | D26: =FV(APP!C15,22*12,-APP!C13,0) -> 962849.51 | E26: =D26*APP!C15 -> 5777.0971
B27: 23 | C27: =APP!C13*23*12 -> 414000 | D27: =FV(APP!C15,23*12,-APP!C13,0) -> 1053114.8 | E27: =D27*APP!C15 -> 6318.689
B28: 24 | C28: =APP!C13*24*12 -> 432000 | D28: =FV(APP!C15,24*12,-APP!C13,0) -> 1150098.1 | E28: =D28*APP!C15 -> 6900.5884
B29: 25 | C29: =APP!C13*25*12 -> 450000 | D29: =FV(APP!C15,25*12,-APP!C13,0) -> 1254299.2 | E29: =D29*APP!C15 -> 7525.7952
B30: 26 | C30: =APP!C13*26*12 -> 468000 | D30: =FV(APP!C15,26*12,-APP!C13,0) -> 1366255.4 | E30: =D30*APP!C15 -> 8197.5325
B31: 27 | C31: =APP!C13*27*12 -> 486000 | D31: =FV(APP!C15,27*12,-APP!C13,0) -> 1486543.9 | E31: =D31*APP!C15 -> 8919.2633
B32: 28 | C32: =APP!C13*28*12 -> 504000 | D32: =FV(APP!C15,28*12,-APP!C13,0) -> 1615784.7 | E32: =D32*APP!C15 -> 9694.7083
B33: 29 | C33: =APP!C13*29*12 -> 522000 | D33: =FV(APP!C15,29*12,-APP!C13,0) -> 1754644.2 | E33: =D33*APP!C15 -> 10527.865
B34: 30 | C34: =APP!C13*30*12 -> 540000 | D34: =FV(APP!C15,30*12,-APP!C13,0) -> 1903838.2 | E34: =D34*APP!C15 -> 11423.029
